{
  "inventory": [
    "exact",
    "GameLogic.AsciiTable",
    "[anonymous]",
    "GameLogic.and_intro",
    "GameLogic.and_def",
    "have",
    "GameLogic.Precedence",
    "GameLogic.and_left",
    "GameLogic.and_right",
    "assumption",
    "constructor",
    "cases",
    "GameLogic.modus_ponens",
    "GameLogic.FunElim",
    "GameLogic.FunIntro",
    "GameLogic.identity",
    "GameLogic.and_comm",
    "GameLogic.imp_trans",
    "apply",
    "intro",
    "repeat",
    "GameLogic.or_inl",
    "GameLogic.or_def",
    "GameLogic.or_inr",
    "GameLogic.or_elim",
    "GameLogic.or_comm",
    "left",
    "right"
  ],
  "openedIntro": true,
  "data": {
    "AndIntro": {
      "1": {
        "code": "exact todo_list\r\n",
        "completed": true,
        "selections": [
          {
            "selectionStartLineNumber": 2,
            "selectionStartColumn": 1,
            "positionLineNumber": 2,
            "positionColumn": 1
          }
        ],
        "help": []
      },
      "2": {
        "code": "exact and_intro p s\r\n",
        "completed": true,
        "selections": [
          {
            "selectionStartLineNumber": 2,
            "selectionStartColumn": 1,
            "positionLineNumber": 2,
            "positionColumn": 1
          }
        ],
        "help": []
      },
      "3": {
        "code": "(have ai := and_intro a i; have ou := and_intro o u)\r\nexact ⟨ai, ou⟩\r\n",
        "completed": true,
        "selections": [
          {
            "selectionStartLineNumber": 3,
            "selectionStartColumn": 1,
            "positionLineNumber": 3,
            "positionColumn": 1
          }
        ],
        "help": []
      },
      "4": {
        "code": "exact vm.left\r\n",
        "completed": true,
        "selections": [
          {
            "selectionStartLineNumber": 2,
            "selectionStartColumn": 1,
            "positionLineNumber": 2,
            "positionColumn": 1
          }
        ],
        "help": []
      },
      "5": {
        "code": "exact h.right\r\n",
        "completed": true,
        "selections": [
          {
            "selectionStartLineNumber": 2,
            "selectionStartColumn": 1,
            "positionLineNumber": 2,
            "positionColumn": 1
          }
        ],
        "help": []
      },
      "6": {
        "code": "exact ⟨h1.left, h2.right⟩\r\n",
        "completed": true,
        "selections": [
          {
            "selectionStartLineNumber": 2,
            "selectionStartColumn": 1,
            "positionLineNumber": 2,
            "positionColumn": 1
          }
        ],
        "help": []
      },
      "7": {
        "code": "exact h.left.right.left.left.right\r\n",
        "completed": true,
        "selections": [
          {
            "selectionStartLineNumber": 2,
            "selectionStartColumn": 1,
            "positionLineNumber": 2,
            "positionColumn": 1
          }
        ],
        "help": []
      },
      "8": {
        "code": "(have ⟨⟨⟨p,s⟩, a⟩,_,⟨c,_⟩,_⟩ := h)\r\nexact ⟨a,c,p,s⟩\r\n",
        "completed": true,
        "selections": [
          {
            "selectionStartLineNumber": 3,
            "selectionStartColumn": 1,
            "positionLineNumber": 3,
            "positionColumn": 1
          }
        ],
        "help": []
      }
    },
    "AndTactic": {
      "1": {
        "code": "assumption\r\n",
        "completed": true,
        "selections": [
          {
            "selectionStartLineNumber": 2,
            "selectionStartColumn": 1,
            "positionLineNumber": 2,
            "positionColumn": 1
          }
        ],
        "help": []
      },
      "2": {
        "code": "constructor\r\n(assumption; assumption)\r\n",
        "completed": true,
        "selections": [
          {
            "selectionStartLineNumber": 3,
            "selectionStartColumn": 1,
            "positionLineNumber": 3,
            "positionColumn": 1
          }
        ],
        "help": []
      },
      "3": {
        "code": "constructor\r\nconstructor\r\nassumption\r\nassumption\r\nconstructor\r\nassumption\r\nassumption\r\n",
        "completed": true,
        "selections": [
          {
            "selectionStartLineNumber": 8,
            "selectionStartColumn": 1,
            "positionLineNumber": 8,
            "positionColumn": 1
          }
        ],
        "help": []
      },
      "4": {
        "code": "cases h\r\nassumption\r\n",
        "completed": true,
        "selections": [
          {
            "selectionStartLineNumber": 3,
            "selectionStartColumn": 1,
            "positionLineNumber": 3,
            "positionColumn": 1
          }
        ],
        "help": []
      },
      "5": {
        "code": "(cases h; assumption)\r\n",
        "completed": true,
        "selections": [
          {
            "selectionStartLineNumber": 2,
            "selectionStartColumn": 1,
            "positionLineNumber": 2,
            "positionColumn": 1
          }
        ],
        "help": []
      },
      "6": {
        "code": "constructor\r\n(cases h1; assumption)\r\n(cases h2; assumption)\r\n",
        "completed": true,
        "selections": [
          {
            "selectionStartLineNumber": 4,
            "selectionStartColumn": 1,
            "positionLineNumber": 4,
            "positionColumn": 1
          }
        ],
        "help": []
      },
      "7": {
        "code": "cases h\r\ncases left\r\ncases right_1\r\ncases left\r\ncases left_2\r\nassumption\r\n",
        "completed": true,
        "selections": [
          {
            "selectionStartLineNumber": 7,
            "selectionStartColumn": 1,
            "positionLineNumber": 7,
            "positionColumn": 1
          }
        ],
        "help": []
      },
      "8": {
        "code": "cases h\r\ncases left\r\ncases left_1\r\ncases right\r\ncases right_3\r\ncases left_2\r\n(constructor; assumption; constructor; assumption; constructor; assumption; assumption)\r\n",
        "completed": true,
        "selections": [
          {
            "selectionStartLineNumber": 8,
            "selectionStartColumn": 1,
            "positionLineNumber": 8,
            "positionColumn": 1
          }
        ],
        "help": []
      }
    },
    "ImpIntro": {
      "1": {
        "code": "-- have c := bakery_service p\r\nexact bakery_service p\r\n",
        "completed": true,
        "selections": [
          {
            "selectionStartLineNumber": 1,
            "selectionStartColumn": 4,
            "positionLineNumber": 1,
            "positionColumn": 4
          }
        ],
        "help": []
      },
      "2": {
        "code": "exact id\r\n",
        "completed": true,
        "selections": [
          {
            "selectionStartLineNumber": 2,
            "selectionStartColumn": 1,
            "positionLineNumber": 2,
            "positionColumn": 1
          }
        ],
        "help": []
      },
      "3": {
        "code": "exact fun ⟨I,S⟩ => ⟨S, I⟩\r\n",
        "completed": true,
        "selections": [
          {
            "selectionStartLineNumber": 2,
            "selectionStartColumn": 1,
            "positionLineNumber": 2,
            "positionColumn": 1
          }
        ],
        "help": []
      },
      "4": {
        "code": "exact h2 ∘ h1\r\n",
        "completed": true,
        "selections": [
          {
            "selectionStartLineNumber": 2,
            "selectionStartColumn": 1,
            "positionLineNumber": 2,
            "positionColumn": 1
          }
        ],
        "help": []
      },
      "5": {
        "code": "exact p |> h1 |> h3 |> h5\r\n",
        "completed": true,
        "selections": [
          {
            "selectionStartLineNumber": 2,
            "selectionStartColumn": 1,
            "positionLineNumber": 2,
            "positionColumn": 1
          }
        ],
        "help": []
      },
      "6": {
        "code": "exact fun c d => ⟨c, d⟩ |> h\r\n",
        "completed": true,
        "selections": [
          {
            "selectionStartLineNumber": 2,
            "selectionStartColumn": 1,
            "positionLineNumber": 2,
            "positionColumn": 1
          }
        ],
        "help": []
      },
      "7": {
        "code": "exact fun ⟨c,d⟩ => h c d\r\n",
        "completed": true,
        "selections": [
          {
            "selectionStartLineNumber": 2,
            "selectionStartColumn": 1,
            "positionLineNumber": 2,
            "positionColumn": 1
          }
        ],
        "help": []
      },
      "8": {
        "code": "exact fun s => ⟨h.left s, h.right s⟩\r\n",
        "completed": true,
        "selections": [
          {
            "selectionStartLineNumber": 2,
            "selectionStartColumn": 1,
            "positionLineNumber": 2,
            "positionColumn": 1
          }
        ],
        "help": []
      },
      "9": {
        "code": "exact fun r => ⟨fun _ => r, fun _ => r⟩\r\n",
        "completed": true,
        "selections": [
          {
            "selectionStartLineNumber": 2,
            "selectionStartColumn": 1,
            "positionLineNumber": 2,
            "positionColumn": 1
          }
        ],
        "help": []
      }
    },
    "ImpTactic": {
      "1": {
        "code": "apply h\r\nassumption\r\n",
        "completed": true,
        "selections": [
          {
            "selectionStartLineNumber": 3,
            "selectionStartColumn": 1,
            "positionLineNumber": 3,
            "positionColumn": 1
          }
        ],
        "help": []
      },
      "2": {
        "code": "intro p\r\nassumption\r\n",
        "completed": true,
        "selections": [
          {
            "selectionStartLineNumber": 3,
            "selectionStartColumn": 1,
            "positionLineNumber": 3,
            "positionColumn": 1
          }
        ],
        "help": []
      },
      "3": {
        "code": "intro pq\r\ncases pq\r\nconstructor\r\n(assumption; assumption)\r\n",
        "completed": true,
        "selections": [
          {
            "selectionStartLineNumber": 5,
            "selectionStartColumn": 1,
            "positionLineNumber": 5,
            "positionColumn": 1
          }
        ],
        "help": []
      },
      "4": {
        "code": "intro c\r\napply h2 ∘ h1 at c\r\nassumption\r\n",
        "completed": true,
        "selections": [
          {
            "selectionStartLineNumber": 4,
            "selectionStartColumn": 1,
            "positionLineNumber": 4,
            "positionColumn": 1
          }
        ],
        "help": []
      },
      "5": {
        "code": "intro p\r\napply (h5 ∘ h3 ∘ h1) at p\r\nassumption\r\n",
        "completed": true,
        "selections": [
          {
            "selectionStartLineNumber": 4,
            "selectionStartColumn": 1,
            "positionLineNumber": 4,
            "positionColumn": 1
          }
        ],
        "help": []
      },
      "6": {
        "code": "intro p\r\nintro q\r\napply h\r\n(constructor; repeat assumption)\r\n",
        "completed": true,
        "selections": [
          {
            "selectionStartLineNumber": 5,
            "selectionStartColumn": 1,
            "positionLineNumber": 5,
            "positionColumn": 1
          }
        ],
        "help": []
      },
      "7": {
        "code": "intro pq\r\napply h\r\ncases pq\r\nrepeat assumption\r\ncases pq\r\nassumption\r\n",
        "completed": true,
        "selections": [
          {
            "selectionStartLineNumber": 7,
            "selectionStartColumn": 1,
            "positionLineNumber": 7,
            "positionColumn": 1
          }
        ],
        "help": []
      },
      "8": {
        "code": "intro p\r\nconstructor\r\napply h.left at p\r\nassumption\r\napply h.right at p\r\nassumption\r\n",
        "completed": true,
        "selections": [
          {
            "selectionStartLineNumber": 7,
            "selectionStartColumn": 1,
            "positionLineNumber": 7,
            "positionColumn": 1
          }
        ],
        "help": []
      },
      "9": {
        "code": "intro q\r\nconstructor\r\nrepeat {intro; assumption}\r\n",
        "completed": true,
        "selections": [
          {
            "selectionStartLineNumber": 4,
            "selectionStartColumn": 1,
            "positionLineNumber": 4,
            "positionColumn": 1
          }
        ],
        "help": []
      }
    },
    "OrIntro": {
      "1": {
        "code": "exact Or.inl s\r\n",
        "completed": true,
        "selections": [
          {
            "selectionStartLineNumber": 2,
            "selectionStartColumn": 1,
            "positionLineNumber": 2,
            "positionColumn": 1
          }
        ],
        "help": []
      },
      "2": {
        "code": "exact Or.inr s\r\n",
        "completed": true,
        "selections": [
          {
            "selectionStartLineNumber": 2,
            "selectionStartColumn": 1,
            "positionLineNumber": 2,
            "positionColumn": 1
          }
        ],
        "help": []
      },
      "3": {
        "code": "have r : B := or_elim h3 h1 h2\r\nexact r\r\n",
        "completed": true,
        "selections": [
          {
            "selectionStartLineNumber": 3,
            "selectionStartColumn": 1,
            "positionLineNumber": 3,
            "positionColumn": 1
          }
        ],
        "help": []
      },
      "4": {
        "code": "exact or_elim h or_inr or_inl\r\n",
        "completed": true,
        "selections": [
          {
            "selectionStartLineNumber": 2,
            "selectionStartColumn": 1,
            "positionLineNumber": 2,
            "positionColumn": 1
          }
        ],
        "help": []
      },
      "5": {
        "code": "exact or_elim h2 (fun c : C => (or_inl (h1 c) : J ∨ R)) (fun r : R => (or_inr r : J ∨ R))\r\n",
        "completed": true,
        "selections": [
          {
            "selectionStartLineNumber": 2,
            "selectionStartColumn": 1,
            "positionLineNumber": 2,
            "positionColumn": 1
          }
        ],
        "help": []
      },
      "6": {
        "code": "(have gh (g:G): G∨H := or_inl g; have gu (g:G): G∨U := or_inl g;)\r\nhave gr (g:G): (G ∨ H) ∧ (G ∨ U) := and_intro (gh g) (gu g)\r\n(have gh (hu:H ∧ U) : (G ∨ H) := or_inr hu.left; have gu (hu:H ∧ U) : (G ∨ U) := or_inr hu.right)\r\nhave hur (hu:H∧U): (G ∨ H) ∧ (G ∨ U) := and_intro (gh hu) (gu hu)\r\nexact or_elim h gr hur\r\n",
        "completed": true,
        "selections": [
          {
            "selectionStartLineNumber": 6,
            "selectionStartColumn": 1,
            "positionLineNumber": 6,
            "positionColumn": 1
          }
        ],
        "help": []
      },
      "7": {
        "code": "-- #check or_elim h.right (fun h1 => and_intro h.left h1) (fun h1 => and_intro h.left h1)\r\nhave gh p : G ∧ H ∨ G ∧ U := or_inl (and_intro h.left p)\r\nhave gu u : G ∧ H ∨ G ∧ U := or_inr (and_intro h.left u)\r\nexact or_elim h.right gh gu",
        "completed": true,
        "selections": [
          {
            "selectionStartLineNumber": 4,
            "selectionStartColumn": 28,
            "positionLineNumber": 4,
            "positionColumn": 28
          }
        ],
        "help": []
      },
      "8": {
        "code": "exact fun ki => or_elim ki (fun k => or_inr (h k)) (fun i => or_inl i)\r\n",
        "completed": true,
        "selections": [
          {
            "selectionStartLineNumber": 1,
            "selectionStartColumn": 70,
            "positionLineNumber": 1,
            "positionColumn": 70
          }
        ],
        "help": []
      }
    },
    "OrTactic": {
      "1": {
        "code": "left\r\nassumption\r\n",
        "completed": true,
        "selections": [
          {
            "selectionStartLineNumber": 3,
            "selectionStartColumn": 1,
            "positionLineNumber": 3,
            "positionColumn": 1
          }
        ],
        "help": []
      },
      "2": {
        "code": "right\r\nassumption",
        "completed": true,
        "selections": [
          {
            "selectionStartLineNumber": 2,
            "selectionStartColumn": 11,
            "positionLineNumber": 2,
            "positionColumn": 11
          }
        ],
        "help": []
      },
      "3": {
        "code": "cases h3\r\napply h1 at h\r\nassumption\r\napply h2 at h\r\nassumption\r\n",
        "completed": true,
        "selections": [
          {
            "selectionStartLineNumber": 6,
            "selectionStartColumn": 1,
            "positionLineNumber": 6,
            "positionColumn": 1
          }
        ],
        "help": []
      },
      "4": {
        "code": "cases h\r\nright\r\nassumption\r\nleft\r\nassumption\r\n",
        "completed": true,
        "selections": [
          {
            "selectionStartLineNumber": 6,
            "selectionStartColumn": 1,
            "positionLineNumber": 6,
            "positionColumn": 1
          }
        ],
        "help": []
      },
      "5": {
        "code": "cases h2\r\napply h1 at h\r\nleft\r\nassumption\r\nright\r\nassumption\r\n",
        "completed": true,
        "selections": [
          {
            "selectionStartLineNumber": 7,
            "selectionStartColumn": 1,
            "positionLineNumber": 7,
            "positionColumn": 1
          }
        ],
        "help": []
      },
      "6": {
        "code": "cases h\r\nconstructor\r\nleft\r\nassumption\r\nleft\r\nassumption\r\nconstructor\r\nright\r\ncases h_1\r\nassumption\r\ncases h_1\r\nright\r\nassumption\r\n",
        "completed": true,
        "selections": [
          {
            "selectionStartLineNumber": 14,
            "selectionStartColumn": 1,
            "positionLineNumber": 14,
            "positionColumn": 1
          }
        ],
        "help": []
      },
      "7": {
        "code": "cases h\r\ncases right\r\nleft\r\nconstructor\r\nassumption\r\nassumption\r\nright\r\nconstructor\r\nassumption\r\nassumption\r\n",
        "completed": true,
        "selections": [
          {
            "selectionStartLineNumber": 11,
            "selectionStartColumn": 1,
            "positionLineNumber": 11,
            "positionColumn": 1
          }
        ],
        "help": []
      },
      "8": {
        "code": "intro qp\r\ncases qp\r\napply h at h_1\r\nright\r\nassumption\r\nleft\r\nassumption\r\n",
        "completed": true,
        "selections": [
          {
            "selectionStartLineNumber": 8,
            "selectionStartColumn": 1,
            "positionLineNumber": 8,
            "positionColumn": 1
          }
        ],
        "help": []
      }
    }
  },
  "difficulty": 2,
  "typewriterMode": true
}